
<annotation>
    <folder>images</folder>
    <filename>potholes79.png</filename>
    <size>
        <width>451</width>
        <height>300</height>
        <depth>3</depth>
    </size>
    <segmented>0</segmented>
    <object>
        <name>pothole</name>
        <pose>Unspecified</pose>
        <truncated>0</truncated>
        <occluded>0</occluded>
        <difficult>0</difficult>
        <bndbox>
            <xmin>124</xmin>
            <ymin>119</ymin>
            <xmax>303</xmax>
            <ymax>205</ymax>
        </bndbox>
    </object>
    <object>
        <name>pothole</name>
        <pose>Unspecified</pose>
        <truncated>0</truncated>
        <occluded>0</occluded>
        <difficult>0</difficult>
        <bndbox>
            <xmin>325</xmin>
            <ymin>87</ymin>
            <xmax>353</xmax>
            <ymax>102</ymax>
        </bndbox>
    </object>
</annotation>